{
    "73": [
        {
            "Name": "DCO trimming",
            "Register": {
                "RegisterAddress": 568,
                "RegisterLSB": 10,
                "RegisterMSB": 15,
                "RegisterValue": 37
            },
            "MeasureValue": 2981300.0,
            "typical": 3000000,
            "MinError": -0.6233333333333333
        },
        {
            "Name": "Aon BG vref 1.2V (VDDA 1.8V) trimming",
            "Register": {
                "RegisterAddress": 596,
                "RegisterLSB": 13,
                "RegisterMSB": 17,
                "RegisterValue": 1
            },
            "MeasureValue": 1.7998252899999998,
            "typical": 1.8,
            "MinError": -0.009706111111124687
        },
        {
            "Name": "Aon vref 0.6V trimming",
            "Register": {
                "RegisterAddress": 596,
                "RegisterLSB": 3,
                "RegisterMSB": 7,
                "RegisterValue": 3
            },
            "MeasureValue": 0.59986789925,
            "typical": 0.6,
            "MinError": -0.022016791666671736
        },
        {
            "Name": "Aon ldo_vref_1p2 trimming",
            "Register": {
                "RegisterAddress": 596,
                "RegisterLSB": 8,
                "RegisterMSB": 12,
                "RegisterValue": 1
            },
            "MeasureValue": 1.2005315525,
            "typical": 1.2,
            "MinError": 0.04429604166666934
        },
        {
            "Name": "LDO1.2 Trimming ",
            "Register": {
                "RegisterAddress": 604,
                "RegisterLSB": 14,
                "RegisterMSB": 19,
                "RegisterValue": 1
            },
            "MeasureValue": 1.1896293675,
            "typical": 1.2,
            "MinError": -0.010370632499999921
        },
        {
            "Name": "Main BG Current Trimming ",
            "Register": {
                "RegisterAddress": 600,
                "RegisterLSB": 6,
                "RegisterMSB": 9,
                "RegisterValue": 1
            },
            "MeasureValue": 1.4966741650000002e-06,
            "typical": 1.5e-06,
            "MinError": -3.3258349999998377e-09
        },
        {},
        {
            "Name": "PH13 IND CS Buffer",
            "Register": {
                "RegisterAddress": 608,
                "RegisterLSB": 29,
                "RegisterMSB": 31,
                "RegisterValue": 5
            },
            "MeasureValue": 0.6981117410000001,
            "typical": 0.7,
            "MinError": -0.0018882589999998922
        },
        {
            "Name": "PH24 IND CS Buffer",
            "Register": {
                "RegisterAddress": 608,
                "RegisterLSB": 26,
                "RegisterMSB": 28,
                "RegisterValue": 0
            },
            "MeasureValue": 0.6971457470000001,
            "typical": 0.7,
            "MinError": -0.0028542529999998623
        }
    ]
}